pingintel_api/__about__.py
pingintel_api/__init__.py
pingintel_api/api_client_base.py
pingintel_api/common_types.py
pingintel_api/constants.py
pingintel_api/pingdataapi_cmd.py
pingintel_api/pingmapsapi_cmd.py
pingintel_api/pingvisionapi_cmd.py
pingintel_api/sovfixerapi_cmd.py
pingintel_api/url_signature_factory.py
pingintel_api/utils.py
pingintel_api/pingdata/pingdata_api_client.py
pingintel_api/pingdata/types.py
pingintel_api/pingmaps/pingmaps_api_client.py
pingintel_api/pingmaps/types.py
pingintel_api/pingvision/pingvision_api_client.py
pingintel_api/pingvision/types.py
pingintel_api/sov_fixer/sov_fixer_api_client.py
pingintel_api/sov_fixer/types.py
pingintel_api-1.3.11.dist-info/METADATA
pingintel_api-1.3.11.dist-info/WHEEL
pingintel_api-1.3.11.dist-info/entry_points.txt
pingintel_api-1.3.11.dist-info/licenses/LICENSE
pingintel_api-1.3.11.dist-info/RECORD
