Metadata-Version: 2.3
Name: pingintel-api
Version: 1.3.11
Summary: Python-based client to Ping Data Intelligence APIs
Project-URL: Homepage, https://github.com/pingintel/pingintel-api
Project-URL: Issues, https://github.com/pingintel/pingintel-api/issues
Author-email: Ping Intel <support@pingintel.com>, Scott Stafford <scott@pingintel.com>
Classifier: License :: OSI Approved :: MIT License
Classifier: Operating System :: OS Independent
Classifier: Programming Language :: Python :: 3
Requires-Python: >=3.11
Requires-Dist: click
Requires-Dist: requests
